autoversioner/__init__.py
autoversioner/autoversioner.py
autoversioner/version.py
autoversioner-2024.6.0.dist-info/LICENSE
autoversioner-2024.6.0.dist-info/METADATA
autoversioner-2024.6.0.dist-info/WHEEL
autoversioner-2024.6.0.dist-info/entry_points.txt
autoversioner-2024.6.0.dist-info/top_level.txt
autoversioner-2024.6.0.dist-info/RECORD
