Metadata-Version: 2.1
Name: autoversioner
Version: 2024.6.0
Summary: Synchronize your subtitle files by shifting the subtitle time (+/-)
Home-page: https://github.com/Knuckles-Team/subsync
Author: Audel Rouhi
Author-email: knucklessg1@gmail.com
License: MIT
Platform: UNKNOWN
Classifier: Development Status :: 5 - Production/Stable
Classifier: License :: Public Domain
Classifier: Environment :: Console
Classifier: Operating System :: POSIX :: Linux
Classifier: Programming Language :: Python :: 3.8
Classifier: Programming Language :: Python :: 3.9
Classifier: Programming Language :: Python :: 3.10
Classifier: Programming Language :: Python :: 3.11
License-File: LICENSE
Requires-Dist: semantic-version (==2.10.0)
